neuro_notifications_client/__init__.py
neuro_notifications_client/client.py
neuro_notifications_client/notifications.py
neuro_notifications_client/py.typed
neuro_notifications_client/schema.py
neuro_notifications_client-25.3.0.dist-info/licenses/LICENSE
neuro_notifications_client-25.3.0.dist-info/METADATA
neuro_notifications_client-25.3.0.dist-info/WHEEL
neuro_notifications_client-25.3.0.dist-info/top_level.txt
neuro_notifications_client-25.3.0.dist-info/RECORD
