Metadata-Version: 2.4
Name: neuro-notifications-client
Version: 25.3.0
Summary: Notifications client for Neu.ro platform services
Home-page: https://github.com/neuro-inc/neuro-notifications-client
License: Apache 2
Classifier: License :: OSI Approved :: Apache Software License
Classifier: Programming Language :: Python :: 3
Requires-Python: >=3.9
License-File: LICENSE
Requires-Dist: aiohttp>=3.7
Requires-Dist: marshmallow>=3.13.0
Dynamic: license-file
